pamela/__init__.py
pamela/client.py
pamela/exceptions.py
pamela/webhooks.py
thisispamela-1.1.2.dist-info/METADATA
thisispamela-1.1.2.dist-info/WHEEL
thisispamela-1.1.2.dist-info/top_level.txt
thisispamela-1.1.2.dist-info/RECORD
