Metadata-Version: 2.4
Name: thisispamela
Version: 1.1.2
Summary: Pamela Enterprise Voice API SDK for Python
Author-email: Pamela <support@thisispamela.com>
License: MIT
Project-URL: Homepage, https://github.com/rtpam/pamela
Classifier: Development Status :: 4 - Beta
Classifier: Intended Audience :: Developers
Classifier: License :: OSI Approved :: MIT License
Classifier: Programming Language :: Python :: 3
Classifier: Programming Language :: Python :: 3.8
Classifier: Programming Language :: Python :: 3.9
Classifier: Programming Language :: Python :: 3.10
Classifier: Programming Language :: Python :: 3.11
Classifier: Programming Language :: Python :: 3.12
Requires-Python: >=3.8
Requires-Dist: requests>=2.28.0
Requires-Dist: urllib3>=1.26.0
